{"cameraMode":{"drawMode":0,"name":"Shaded","section":"Shading Mode"},"sceneLighting":false,"audioPlay":false,"sceneViewState":{"showFog":true,"showMaterialUpdate":false,"showSkybox":false,"showFlares":true,"showImageEffects":true,"showParticleSystems":true},"in2DMode":false,"pivot":{"x":237.6538543701172,"y":42.60746765136719,"z":189.12515258789063},"rotation":{"x":-0.08449649810791016,"y":0.914743185043335,"z":-0.2609300911426544,"w":-0.29693156480789187},"size":24.551137924194337,"orthographic":false}